rmmtools/__init__.py
rmmtools/rmm_util_accessor/__init__.py
rmmtools/rmm_util_accessor/accessor_base.py
rmmtools/rmm_util_accessor/dataframe_accessor.py
rmmtools/rmm_util_accessor/series_accessor.py
rmmtools/util/__init__.py
rmmtools/util/data_processor.py
rmmtools/util/errors.py
rmmtools/util/filters.py
rmmtools/util/parser.py
rmmtools/util/timer.py
rmmtools/util/viz.py
rmmtools/util/general/__init__.py
rmmtools/util/general/datetime_util.py
rmmtools/util/general/general_util.py
rmmtools/util/general/pandas_util.py
rmmtools-0.1.0.dist-info/METADATA
rmmtools-0.1.0.dist-info/WHEEL
rmmtools-0.1.0.dist-info/licenses/LICENSE
rmmtools-0.1.0.dist-info/RECORD
